odd_cli/__init__.py
odd_cli/__version__.py
odd_cli/apps/__init__.py
odd_cli/apps/metadata.py
odd_cli/apps/tokens.py
odd_cli/client.py
odd_cli/error.py
odd_cli/logger.py
odd_cli/main.py
odd_cli/reader/__init__.py
odd_cli/reader/csv.py
odd_cli/reader/mapper/__init__.py
odd_cli/reader/mapper/field.py
odd_cli/reader/mapper/table.py
odd_cli/reader/models/__init__.py
odd_cli/reader/models/field.py
odd_cli/reader/models/table.py
odd_cli/reader/reader.py
odd_cli-0.2.12.dist-info/entry_points.txt
odd_cli-0.2.12.dist-info/LICENSE
odd_cli-0.2.12.dist-info/WHEEL
odd_cli-0.2.12.dist-info/METADATA
odd_cli-0.2.12.dist-info/RECORD
